{
  "C11XU": {
    "topic_tags": [
      "advanced/optimization-and-duality"
    ],
    "patterns": [
      "xor-independence",
      "forest selection",
      "augmenting exchange"
    ],
    "tracks": [
      "VN SPOJ",
      "OI-style"
    ]
  },
  "CRYPTKEY": {
    "topic_tags": [
      "math/number-theory-basics"
    ],
    "patterns": [
      "gcd-lcm closure",
      "prime-power characterization",
      "constructibility"
    ],
    "tracks": [
      "VN SPOJ",
      "OI-style"
    ]
  },
  "COMPANYQUERIES2": {
    "topic_tags": [
      "graphs/trees"
    ],
    "patterns": [
      "binary lifting",
      "depth equalization",
      "lowest common ancestor"
    ],
    "tracks": [
      "CSES",
      "Tree algorithms"
    ]
  },
  "CVP00001": {
    "topic_tags": [
      "foundations/prefix-sums"
    ],
    "patterns": [
      "circular updates",
      "range-add point-query",
      "query-from-initial-state"
    ],
    "tracks": [
      "VN SPOJ",
      "OI-style"
    ]
  },
  "FFLOW": {
    "topic_tags": [],
    "patterns": [
      "maximum flow",
      "undirected capacities",
      "capacity scaling"
    ],
    "tracks": [
      "VN SPOJ",
      "ICPC-style"
    ]
  },
  "COUNTINGNUMBERS": {
    "topic_tags": [],
    "patterns": [
      "digit dp",
      "previous digit state",
      "range counting"
    ],
    "tracks": [
      "CSES",
      "Dynamic programming"
    ]
  },
  "CONCERTTICKETS": {
    "topic_tags": [],
    "patterns": [
      "multiset predecessor",
      "erase one occurrence",
      "greedy ticket assignment"
    ],
    "tracks": [
      "CSES",
      "Sorting and searching"
    ]
  },
  "DISTINCTVALUESQUERIES": {
    "topic_tags": [
      "data-structures/fenwick-tree"
    ],
    "patterns": [
      "offline right-endpoint sweep",
      "last occurrence activation",
      "fenwick range count"
    ],
    "tracks": [
      "CSES",
      "Range queries"
    ]
  },
  "FACTORYMACHINES": {
    "topic_tags": [],
    "patterns": [
      "answer binary search",
      "monotone feasibility",
      "production rate accumulation"
    ],
    "tracks": [
      "CSES",
      "Sorting and searching"
    ]
  },
  "EXPONENTIATION2": {
    "topic_tags": [],
    "patterns": [
      "binary exponentiation",
      "fermat exponent reduction",
      "zero exponent edge case"
    ],
    "tracks": [
      "CSES",
      "Mathematics"
    ]
  },
  "FINDINGBORDERS": {
    "topic_tags": [],
    "patterns": [
      "rolling hash",
      "prefix-suffix equality",
      "proper borders enumeration"
    ],
    "tracks": [
      "CSES",
      "String algorithms"
    ]
  },
  "FINDINGPATTERNS": {
    "topic_tags": [
      "strings/trie"
    ],
    "patterns": [
      "aho-corasick automaton",
      "failure links",
      "multi-pattern presence queries"
    ],
    "tracks": [
      "CSES",
      "String algorithms"
    ]
  },
  "KINGDOMS": {
    "topic_tags": [
      "graphs/trees",
      "geometry/polygon-area-point-location"
    ],
    "patterns": [
      "laminar regions",
      "sweep events",
      "containment tree"
    ],
    "tracks": [
      "VN SPOJ",
      "OI-style"
    ]
  },
  "LAMP": {
    "topic_tags": [
      "math/gcd-lcm",
      "combinatorics/inclusion-exclusion"
    ],
    "patterns": [
      "density formula",
      "pairwise coprime products",
      "big integer fractions"
    ],
    "tracks": [
      "VN SPOJ",
      "OI-style"
    ]
  },
  "MCQUERY": {
    "topic_tags": [
      "data-structures/dsu",
      "graphs/trees",
      "graphs/gomory-hu"
    ],
    "patterns": [
      "all-pairs min-cut",
      "cut tree",
      "count pairs by threshold"
    ],
    "tracks": [
      "VN SPOJ",
      "ICPC-style"
    ]
  },
  "MINCOST": {
    "topic_tags": [
      "graphs/min-cost-flow"
    ],
    "patterns": [
      "transportation network",
      "flow reconstruction",
      "duplicate-edge overwrite"
    ],
    "tracks": [
      "VN SPOJ",
      "ICPC-style"
    ]
  },
  "MESSAGEROUTE": {
    "topic_tags": [
      "graphs/graph-modeling"
    ],
    "patterns": [
      "breadth-first search",
      "unweighted shortest path",
      "parent reconstruction"
    ],
    "tracks": [
      "CSES",
      "Graph algorithms"
    ]
  },
  "COURSESCHEDULE": {
    "topic_tags": [],
    "patterns": [
      "kahn topological sort",
      "indegree peeling",
      "cycle by failed ordering"
    ],
    "tracks": [
      "CSES",
      "Graph algorithms"
    ]
  },
  "MTREECOL": {
    "topic_tags": [],
    "patterns": [
      "ratio greedy",
      "tree contraction",
      "exchange argument"
    ],
    "tracks": [
      "VN SPOJ",
      "OI-style"
    ]
  },
  "MOVIEFESTIVAL": {
    "topic_tags": [],
    "patterns": [
      "finish-time sorting",
      "interval scheduling",
      "exchange argument greedy"
    ],
    "tracks": [
      "CSES",
      "Sorting and searching"
    ]
  },
  "POST2": {
    "topic_tags": [],
    "patterns": [
      "convolution",
      "digit aggregation",
      "big integer addition"
    ],
    "tracks": [
      "VN SPOJ",
      "ICPC-style"
    ]
  },
  "PRAVO": {
    "topic_tags": [
      "geometry/counting-geometry",
      "geometry/vector-orientation"
    ],
    "patterns": [
      "count right triangles",
      "normalized directions",
      "perpendicular pairing"
    ],
    "tracks": [
      "VN SPOJ",
      "OI-style"
    ]
  },
  "QBFLOWER": {
    "topic_tags": [],
    "patterns": [
      "minimum edge cover",
      "general matching",
      "graph transformation"
    ],
    "tracks": [
      "VN SPOJ",
      "OI-style"
    ]
  },
  "QOS": {
    "topic_tags": [
      "dp/foundations"
    ],
    "patterns": [
      "shortest path plus dp",
      "kth lexicographic path",
      "bounded slack states"
    ],
    "tracks": [
      "VN SPOJ",
      "OI-style"
    ]
  },
  "ROADREPARATION": {
    "topic_tags": [],
    "patterns": [
      "kruskal mst",
      "connectivity check",
      "cut property greedy"
    ],
    "tracks": [
      "CSES",
      "Graph algorithms"
    ]
  },
  "STRINGMATCHING": {
    "topic_tags": [],
    "patterns": [
      "prefix function",
      "border fallback",
      "overlapping occurrence counting"
    ],
    "tracks": [
      "CSES",
      "String algorithms"
    ]
  },
  "STRINGFUNCTIONS": {
    "topic_tags": [
      "strings/kmp"
    ],
    "patterns": [
      "z function",
      "prefix function",
      "prefix structure diagnostics"
    ],
    "tracks": [
      "CSES",
      "String algorithms"
    ]
  },
  "TFIELD": {
    "topic_tags": [
      "foundations/two-pointers",
      "geometry/polygon-area-point-location"
    ],
    "patterns": [
      "nested polygons",
      "weighted sliding window",
      "shoelace preprocessing"
    ],
    "tracks": [
      "VN SPOJ",
      "OI-style"
    ]
  },
  "VMMARBLE": {
    "topic_tags": [
      "advanced/constructive"
    ],
    "patterns": [
      "final-color assignment",
      "residual-state dp",
      "capacity-2 moves"
    ],
    "tracks": [
      "VN SPOJ",
      "OI-style"
    ]
  },
  "VMCOINS": {
    "topic_tags": [
      "geometry/vector-orientation"
    ],
    "patterns": [
      "promise-driven constructive",
      "translation matching",
      "small residual search"
    ],
    "tracks": [
      "VN SPOJ",
      "OI-style"
    ]
  },
  "VMSCALE": {
    "topic_tags": [
      "math/number-theory-basics"
    ],
    "patterns": [
      "budget dp",
      "balanced ternary",
      "decision-tree optimization"
    ],
    "tracks": [
      "VN SPOJ",
      "OI-style"
    ]
  },
  "VMWTREE": {
    "topic_tags": [
      "data-structures/segment-tree",
      "graphs/hld"
    ],
    "patterns": [
      "path reverse",
      "path sequence queries",
      "heavy-light decomposition"
    ],
    "tracks": [
      "VN SPOJ",
      "OI-style"
    ]
  },
  "VODIVIDE": {
    "topic_tags": [],
    "patterns": [
      "prefix quota greedy",
      "heap maintenance",
      "pair reconstruction"
    ],
    "tracks": [
      "VN SPOJ",
      "OI-style"
    ]
  },
  "VOITSORT": {
    "topic_tags": [
      "graphs/trees"
    ],
    "patterns": [
      "lexicographic enumeration",
      "stack-sortability",
      "cartesian tree view"
    ],
    "tracks": [
      "VN SPOJ",
      "OI-style"
    ]
  },
  "VOSFENCE": {
    "topic_tags": [
      "combinatorics/counting-basics",
      "combinatorics/inclusion-exclusion"
    ],
    "patterns": [
      "bounded compositions",
      "run decomposition",
      "gap distribution"
    ],
    "tracks": [
      "VN SPOJ",
      "OI-style"
    ]
  },
  "VOSTRIP": {
    "topic_tags": [
      "dp/tree-dp",
      "graphs/trees"
    ],
    "patterns": [
      "tree endpoint pairing",
      "path decomposition",
      "local imbalance formula"
    ],
    "tracks": [
      "VN SPOJ",
      "OI-style"
    ]
  },
  "VOTELPH": {
    "topic_tags": [
      "geometry/polygon-area-point-location"
    ],
    "patterns": [
      "piecewise maximum",
      "endpoint preprocessing",
      "parabola envelopes"
    ],
    "tracks": [
      "VN SPOJ",
      "ICPC-style"
    ]
  },
  "WORDCOMBINATIONS": {
    "topic_tags": [],
    "patterns": [
      "trie plus dp",
      "dictionary segmentation",
      "suffix counting"
    ],
    "tracks": [
      "CSES",
      "String algorithms"
    ]
  }
}
